[{
  "ClientName": "Red Company ",
  "ContractingName": null,
  "JobCode": "F44",
  "JobDescription": "Black Job",
  "TaskCode": null,
  "TaskDescription": null,
  "Id": "59809add6a3fa16b96434cc1",
  "ParentId": "598099676a3fa16b96434cac",
  "EmployeeId": "598097ea6a3fa16b96434c9a",
  "TypeId": "5979f244f77bfede5cb6f281",
  "Description": "Impostazione",
  "Date": "2017-08-12T00:00:00Z",
  "WorkedHours": 8.0,
  "IsDeleted": false
}, {
  "ClientName": "Red Company ",
  "ContractingName": "Nerd Company",
  "JobCode": "F33",
  "JobDescription": "Red Job",
  "TaskCode": "M1",
  "TaskDescription": "Red Task One",
  "Id": "59809af56a3fa16b96434cc2",
  "ParentId": "59809a436a3fa16b96434cb9",
  "EmployeeId": "598097ea6a3fa16b96434c9a",
  "TypeId": "5979f244f77bfede5cb6f281",
  "Description": "Impostazione",
  "Date": "2017-08-11T00:00:00Z",
  "WorkedHours": 8.0,
  "IsDeleted": false
}, {
  "ClientName": "Red Company ",
  "ContractingName": "Nerd Company",
  "JobCode": "F33",
  "JobDescription": "Red Job",
  "TaskCode": "M1",
  "TaskDescription": "Red Task One",
  "Id": "59809afc6a3fa16b96434cc3",
  "ParentId": "59809a436a3fa16b96434cb9",
  "EmployeeId": "598097ea6a3fa16b96434c9a",
  "TypeId": "5979f244f77bfede5cb6f281",
  "Description": "Impostazione",
  "Date": "2017-08-10T00:00:00Z",
  "WorkedHours": 8.0,
  "IsDeleted": false
}, {
  "ClientName": "Red Company ",
  "ContractingName": null,
  "JobCode": "F44",
  "JobDescription": "Black Job",
  "TaskCode": null,
  "TaskDescription": null,
  "Id": "59809b046a3fa16b96434cc4",
  "ParentId": "598099676a3fa16b96434cac",
  "EmployeeId": "598097ea6a3fa16b96434c9a",
  "TypeId": "5979f244f77bfede5cb6f281",
  "Description": "Impostazione",
  "Date": "2017-08-09T00:00:00Z",
  "WorkedHours": 8.0,
  "IsDeleted": false
}, {
  "ClientName": "Red Company ",
  "ContractingName": null,
  "JobCode": "F44",
  "JobDescription": "Black Job",
  "TaskCode": null,
  "TaskDescription": null,
  "Id": "59809b0f6a3fa16b96434cc5",
  "ParentId": "598099676a3fa16b96434cac",
  "EmployeeId": "598097ea6a3fa16b96434c9a",
  "TypeId": "5979f244f77bfede5cb6f281",
  "Description": "Impostazione",
  "Date": "2017-08-13T00:00:00Z",
  "WorkedHours": 8.0,
  "IsDeleted": false
}, {
  "ClientName": "Red Company ",
  "ContractingName": "Nerd Company",
  "JobCode": "F33",
  "JobDescription": "Red Job",
  "TaskCode": "M3",
  "TaskDescription": "Red Task Three",
  "Id": "59809b3c6a3fa16b96434ccb",
  "ParentId": "59809a436a3fa16b96434cbb",
  "EmployeeId": "598097ea6a3fa16b96434c9a",
  "TypeId": "5979f22bf77bfede5cb6f27f",
  "Description": "Cablaggio Porte",
  "Date": "2017-08-11T00:00:00Z",
  "WorkedHours": 8.0,
  "IsDeleted": false
}, {
  "ClientName": "Red Company ",
  "ContractingName": null,
  "JobCode": "F44",
  "JobDescription": "Black Job",
  "TaskCode": null,
  "TaskDescription": null,
  "Id": "59809b466a3fa16b96434ccc",
  "ParentId": "598099676a3fa16b96434cac",
  "EmployeeId": "598097ea6a3fa16b96434c9a",
  "TypeId": "5979f21ff77bfede5cb6f27d",
  "Description": "Bordomacchina",
  "Date": "2017-08-12T00:00:00Z",
  "WorkedHours": 8.0,
  "IsDeleted": false
}]
